Metadata-Version: 2.1
Name: yandex-images-download
Version: 1.0.4
Summary: Python Script to download images from Yandex.Images
Home-page: https://github.com/bobokvsky/yandex-images-download
Author: Alexander Kozlov
Author-email: alexander.kozlovsky.m@gmail.com
License: MIT
Download-URL: https://github.com/bobokvsky/yandex-images-download/archive/v1.0.4.tar.gz
Keywords: yandex images download save terminal command-line scrapper
Platform: UNKNOWN
Classifier: Development Status :: 4 - Beta
Classifier: Intended Audience :: Developers
Classifier: License :: OSI Approved :: MIT License
Classifier: Programming Language :: Python :: 3.7
